ring-counter.v
module ring_counter4(
  input wire clk,
  input wire reset,
  input wire enable,
  output reg A,
  output reg B,
  output reg C,
  output reg D);
 
 
always @(posedge clk) begin
  if (reset) begin
    B = 0;
    C = 0;
    D = 0;
    A = 1;
  end
  else if (enable) begin
    if (A) begin
      A = 0;
      C = 0;
      D = 0;
      B = 1;
    end
    else if (B) begin
      A = 0;
      B = 0;
      D = 0;
      C = 1;
    end
    else if (C) begin
      A = 0;
      B = 0;
      C = 0;
      D = 1;
    end
    else if (D) begin
      B = 0;
      C = 0;
      D = 0;
      A = 1;
    end
  end
 
end
 
endmodule

deteccionBoton.v
module deteccionBoton(
  input wire enable,
  input wire R1, 
  input wire R2, 
  input wire R3,
  input wire R4,
  output reg botonApretado);
 
 //Necesito que sea independiente de Clk.
 // @(*) hace que sea un bloque combinacional
always @(*) begin
  if (enable) begin
    if (R1 || R2 || R3 || R4) begin
      botonApretado = 1;
    end 
    else begin
      botonApretado = 0;
    end
  end
end
 
endmodule

testbench-deteccionBoton.v
`timescale 1ns/10ps

module testbenchBoton;
// Variable RingCounter
reg clk, reset, enable;
wire C1, C2, C3, C4;

reg A, B, C, D;
wire boton;

deteccionBoton detectar(enable, C1, C2, C3, D, boton);
ring_counter4 select_col(clk, reset, enable, C1, C2, C3, C4);

initial begin
    enable = 0;
    A = 0;
    B = 0;
    C = 0;
    D = 0;
    clk = 0;
    reset = 1;
end

always
    #5 clk = ~clk;

initial begin
    // vvp nombre.out
    $dumpfile("SimulacionRingCounter.vcd"); 
    $dumpvars(1);

    #12 reset = 0;
    #10 enable = 1;

    #200 $finish;
end

endmodule

SimulacionRingCounter.vcd
$date
	Thu Nov 07 20:16:44 2024
$end
$version
	Icarus Verilog
$end
$timescale
	10ps
$end
$scope module testbenchBoton $end
$var wire 1 ! boton $end
$var wire 1 " C4 $end
$var wire 1 # C3 $end
$var wire 1 $ C2 $end
$var wire 1 % C1 $end
$var reg 1 & A $end
$var reg 1 ' B $end
$var reg 1 ( C $end
$var reg 1 ) D $end
$var reg 1 * clk $end
$var reg 1 + enable $end
$var reg 1 , reset $end
$upscope $end
$enddefinitions $end
$comment Show the parameter values. $end
$dumpall
$end
#0
$dumpvars
1,
0+
0*
0)
0(
0'
0&
x%
x$
x#
x"
x!
$end
#500
1%
0"
0#
0$
1*
#1000
0*
#1200
0,
#1500
1*
#2000
0*
#2200
1!
1+
#2500
1$
0%
1*
#3000
0*
#3500
1#
0$
1*
#4000
0*
#4500
0!
1"
0#
1*
#5000
0*
#5500
1!
1%
0"
1*
#6000
0*
#6500
1$
0%
1*
#7000
0*
#7500
1#
0$
1*
#8000
0*
#8500
0!
1"
0#
1*
#9000
0*
#9500
1!
1%
0"
1*
#10000
0*
#10500
1$
0%
1*
#11000
0*
#11500
1#
0$
1*
#12000
0*
#12500
0!
1"
0#
1*
#13000
0*
#13500
1!
1%
0"
1*
#14000
0*
#14500
1$
0%
1*
#15000
0*
#15500
1#
0$
1*
#16000
0*
#16500
0!
1"
0#
1*
#17000
0*
#17500
1!
1%
0"
1*
#18000
0*
#18500
1$
0%
1*
#19000
0*
#19500
1#
0$
1*
#20000
0*
#20500
0!
1"
0#
1*
#21000
0*
#21500
1!
1%
0"
1*
