whichKey.v
module whichKey (
    input wire rst,
    input wire [3:0] key_pressed,   // Entrada: tecla traducida (salida de `traduccion_teclado`)
    output reg is_number,           // Salida: 1 si es número (0–9), 0 si es operador
    output reg is_op,               // Señal alta si es un operador (A, B, etc.)
    output reg is_c,                // Señal alta si es 'C'
    output reg is_equ,              // Señal alta si es 'D' (<=)
    output reg [1:0] operator       // Identificador del operador (A<=2'b01, B<=2'b10, etc.)
);

always @(*) begin

    if(rst) begin
        is_number <= 0;    
        is_op <= 0;        
        is_c <= 0;         
        is_equ <= 0;        
        operator <= 2'b00;
    end

    // Evaluar la tecla presionada
    case (key_pressed)
        // Números (0-9)
        4'b0000, // 0
        4'b0001, // 1
        4'b0010, // 2
        4'b0011, // 3
        4'b0100, // 4
        4'b0101, // 5
        4'b0110, // 6
        4'b0111, // 7
        4'b1000, // 8
        4'b1001: // 9
        begin
            is_number <= 1;
            operator <= 2'b00;
            is_op <= 0;
            is_equ <= 0;
            is_c <= 0;
        end
            

        // Operador A
        4'b1010: begin
            operator <= 2'b01;
            is_op <= 1;
            is_number <= 0;
            is_equ <= 0;
            is_c <= 0;
        end

        // Operador B
        4'b1011: begin
            operator <= 2'b10;
            is_op <= 1;
            is_number <= 0;
            is_equ <= 0;
            is_c <= 0;
        end

        // Operador C
        4'b1100: begin
            is_c <= 1;
            is_number <= 0;
            is_equ <= 0;
            operator <= 2'b00;
            is_op <= 0;
            is_equ <= 0;
        end

        // Operador D (=)
        4'b1101: begin
            is_equ <= 0;
            is_number <= 0;
            operator <= 2'b00;
            is_op <= 0;
            is_equ <= 1;
            is_c <= 0;
            
        end

        // Operadores especiales (* y #)
        4'b1110, // *
        4'b1111: // # 
        begin
            is_equ <= 0;
            is_number <= 0;
            operator <= 2'b00;
            is_op <= 0;
            is_equ <= 0;
            is_c <= 0;
        end
            

        default: begin
            // Valor por defecto
            is_number <= 0;
            is_op <= 0;
            is_c <= 0;
            is_equ <= 0;
            operator <= 2'b00;
        end
    endcase
end

endmodule

testbench/testbenchwhichKey.v
`timescale 1ns / 1ps

module whichKey_tb;

    // Entradas
    reg rst;
    reg [3:0] key_pressed;

    // Salidas
    wire is_number;
    wire is_op;
    wire is_c;
    wire is_equ;
    wire [1:0] operator;

    // Instancia del módulo bajo prueba (UUT)
    whichKey uut (
        .rst(rst),
        .key_pressed(key_pressed),
        .is_number(is_number),
        .is_op(is_op),
        .is_c(is_c),
        .is_equ(is_equ),
        .operator(operator)
    );

    // Procedimiento inicial
    initial begin
        $dumpfile("./testbench/out/testbenchwhichKey.vcd");
        $dumpvars(2);

        rst = 1;
        #10;
        rst =0;
        // Inicialización de la señal de entrada
        key_pressed = 4'b0000; // Prueba para el número 0
        #10;
        
        key_pressed = 4'b0001; // Prueba para el número 1
        #10;

        key_pressed = 4'b1010; // Prueba para el operador A
        #10;

        key_pressed = 4'b1011; // Prueba para el operador B
        #10;

        key_pressed = 4'b1100; // Prueba para el operador C
        #10;

        key_pressed = 4'b1101; // Prueba para el operador D (<=)
        #10;

        key_pressed = 4'b1110; // Prueba para el operador especial (*)
        #10;

        key_pressed = 4'b1111; // Prueba para el operador especial (#)
        #10;

        key_pressed = 4'b1001; // Prueba para el número 9
        #10;

        key_pressed = 4'b0101; // Prueba para el número 5
        #10;

        key_pressed = 4'b0111; // Prueba para el número 7
        #10;

        key_pressed = 4'b0000; // Prueba para restablecer a 0
        #10;

        // Finalización de la simulación
        #100 $finish;
    end

    // Monitor para observar señales en tiempo real
    

endmodule

testbench/out/testbenchwhichKey.vcd
$date
	Sat Nov 30 17:27:27 2024
$end
$version
	Icarus Verilog
$end
$timescale
	1ps
$end
$scope module whichKey_tb $end
$var wire 2 ! operator [1:0] $end
$var wire 1 " is_op $end
$var wire 1 # is_number $end
$var wire 1 $ is_equ $end
$var wire 1 % is_c $end
$var reg 4 & key_pressed [3:0] $end
$var reg 1 ' rst $end
$scope module uut $end
$var wire 4 ( key_pressed [3:0] $end
$var wire 1 ' rst $end
$var reg 1 % is_c $end
$var reg 1 $ is_equ $end
$var reg 1 # is_number $end
$var reg 1 " is_op $end
$var reg 2 ) operator [1:0] $end
$upscope $end
$upscope $end
$enddefinitions $end
$comment Show the parameter values. $end
$dumpall
$end
#0
$dumpvars
b0 )
bx (
1'
bx &
0%
0$
0#
0"
b0 !
$end
#10000
1#
b0 &
b0 (
0'
#20000
b1 &
b1 (
#30000
0#
1"
b1 !
b1 )
b1010 &
b1010 (
#40000
b10 !
b10 )
b1011 &
b1011 (
#50000
0"
b0 !
b0 )
1%
b1100 &
b1100 (
#60000
0%
1$
b1101 &
b1101 (
#70000
0$
b1110 &
b1110 (
#80000
b1111 &
b1111 (
#90000
1#
b1001 &
b1001 (
#100000
b101 &
b101 (
#110000
b111 &
b111 (
#120000
b0 &
b0 (
