sincronize.v
module sincronize (
    input wire clk,          // Reloj
    input wire key_press,    // Entrada de la tecla
    output reg key_detect,    // Señal de detección de flanco
    input wire rst
);

    reg key_pressA; // Estado anterior de la tecla

    always @(posedge clk) begin

        if(rst)
            begin
                key_pressA <= 0;
                key_detect <= 0;
            end
        else
            begin
            // Detectar un flanco ascendente en key_press
                if (key_press == 1 && key_pressA == 0) 
                key_detect <= 1;  // Flanco ascendente detectado
            else 
                key_detect <= 0;  // No hay flanco ascendente

            // Actualizar el estado anterior
            key_pressA <= key_press;        
            end

        
    end

endmodule

testbench/testbenchsincronize.v
`timescale 1ns / 1ps

module sincronize_tb;

    // Entradas
    reg clk;
    reg key_press;
    reg rst;

    // Salidas
    wire key_detect;

    // Instancia del módulo sincronize
    sincronize uut (
        .clk(clk),
        .key_press(key_press),
        .key_detect(key_detect),
        .rst(rst)
    );

    // Generador de reloj (50 MHz -> Periodo = 20 ns)
    always #10 clk = ~clk;

    // Procedimiento inicial
    initial begin
        $dumpfile("./testbench/out/testbenchsincronize.vcd");
        $dumpvars(2);

        // Inicialización de señales
        clk = 0;
        key_press = 0;
        rst = 1;  // Reset activo

        // Liberar reset después de 40 ns
        #40;
        rst = 0;

        // Simular flancos en la señal key_press
        #20 key_press = 1;  // Flanco ascendente
        #20 key_press = 0;  // Flanco descendente
        #30 key_press = 1;  // Flanco ascendente
        #30 key_press = 0;  // Flanco descendente
        #40 key_press = 1;  // Flanco ascendente
        #40 key_press = 0;  // Flanco descendente
        #50 key_press = 1;  // Flanco ascendente
        #50 key_press = 0;  // Flanco descendente


        // Reactivar reset
        #20 rst = 1;
        #20 rst = 0;

        // Simular más flancos en key_press
        #30 key_press = 1;  // Flanco ascendente
        #30 key_press = 0;  // Flanco descendente

        // Finalizar simulación
        #100 $finish;
    end

endmodule

testbench/out/testbenchsincronize.vcd
$date
	Sat Nov 30 17:20:28 2024
$end
$version
	Icarus Verilog
$end
$timescale
	1ps
$end
$scope module sincronize_tb $end
$var wire 1 ! key_detect $end
$var reg 1 " clk $end
$var reg 1 # key_press $end
$var reg 1 $ rst $end
$scope module uut $end
$var wire 1 " clk $end
$var wire 1 # key_press $end
$var wire 1 $ rst $end
$var reg 1 ! key_detect $end
$var reg 1 % key_pressA $end
$upscope $end
$upscope $end
$enddefinitions $end
$comment Show the parameter values. $end
$dumpall
$end
#0
$dumpvars
x%
1$
0#
0"
x!
$end
#10000
0!
0%
1"
#20000
0"
#30000
1"
#40000
0"
0$
#50000
1"
#60000
0"
1#
#70000
1%
1!
1"
#80000
0"
0#
#90000
0%
0!
1"
#100000
0"
#110000
1%
1!
1"
1#
#120000
0"
#130000
0!
1"
#140000
0"
0#
#150000
0%
1"
#160000
0"
#170000
1"
#180000
0"
1#
#190000
1%
1!
1"
#200000
0"
#210000
0!
1"
#220000
0"
0#
#230000
0%
1"
#240000
0"
#250000
1"
#260000
0"
#270000
1%
1!
1"
1#
#280000
0"
#290000
0!
1"
#300000
0"
#310000
1"
#320000
0"
0#
#330000
0%
1"
#340000
0"
1$
#350000
1"
#360000
0"
0$
#370000
1"
#380000
0"
#390000
1%
1!
1"
1#
#400000
0"
#410000
0!
1"
#420000
0"
0#
#430000
0%
1"
