deteccionBoton.v
// Autor: @SantinoAggosti
module deteccionBoton(
  input wire enable,
  input wire R1, 
  input wire R2, 
  input wire R3,
  input wire R4,
  output reg botonApretado);
 

 //Necesito que sea independiente de Clk.
 // @(*) hace que sea un bloque combinacional
always @(*) begin
  if (enable) begin
    if (R1 || R2 || R3 || R4) begin
      botonApretado = 1;
    end 
    else begin
      botonApretado = 0;
    end
  end
end
 
endmodule

ring-counter.v
module ring_counter(
  input wire clk,
  input wire reset,
  input wire enable,
  output reg A,
  output reg B,
  output reg C,
  output reg D);
 
always @(posedge clk) begin
  if (reset) begin
    B = 0;
    C = 0;
    D = 0;
    A = 1;
  end
  else if (enable) begin
    if (A) begin
      A = 0;
      C = 0;
      D = 0;
      B = 1;
    end
    else if (B) begin
      A = 0;
      B = 0;
      D = 0;
      C = 1;
    end
    else if (C) begin
      A = 0;
      B = 0;
      C = 0;
      D = 1;
    end
    else if (D) begin
      B = 0;
      C = 0;
      D = 0;
      A = 1;
    end
  end
 
end
 
endmodule

teclado.v
module teclado(
  input wire enable,
  input wire clk,
  input wire reset,
  input wire [3:0] filas,
  output wire [3:0] columnas,
  output reg [4:0] indice_boton, // Primeros 3 bits: columna | Siguientes 3 bits: fila
  output reg [2:0] columna_actual, // Debe ser un vector, no un arreglo
  output reg [2:0] fila_actual,   // Debe ser un vector, no un arreglo
  output wire button_pressed
);

  // Instancias de módulos
  ring_counter ring(
    .clk(clk), 
    .reset(reset), 
    .enable(enable), 
    .A(columnas[0]),
    .B(columnas[1]),
    .C(columnas[2]),
    .D(columnas[3])
  );
  
  deteccionBoton detectar_boton(
    .enable(enable), 
    .R1(filas[0]), 
    .R2(filas[1]), 
    .R3(filas[2]), 
    .R4(filas[3]), 
    .botonApretado(button_pressed)
  );

initial begin
  indice_boton = 5'b10000;
  columna_actual = 3'b111;
  fila_actual = 3'b111;
end


  // Lógica combinacional para detectar la columna actual
  always @(*) begin
    if (enable) begin
      case (columnas)
        4'b0001: columna_actual <= 3'b000; // Primera columna
        4'b0010: columna_actual <= 3'b001; // Segunda columna
        4'b0100: columna_actual <= 3'b010; // Tercera columna
        4'b1000: columna_actual <= 3'b011; // Cuarta columna
        4'b0000: columna_actual <= 3'b111; // Ninguna columna activa
        default: columna_actual <= 3'b111; // Error
      endcase
    end else begin
      columna_actual <= 3'b111; // Por defecto: ninguna columna activa
    end

    if (button_pressed) begin
      case (filas)
        4'b0001: fila_actual <= 3'b000; // Primera fila
        4'b0010: fila_actual <= 3'b001; // Segunda fila
        4'b0100: fila_actual <= 3'b010; // Tercera fila
        4'b1000: fila_actual <= 3'b011; // Cuarta fila
        4'b0000: fila_actual <= 3'b111; // Ninguna fila activa
        default: fila_actual <= 3'b111; // Por defecto
      endcase
    end else begin
      fila_actual <= 3'b111; // Ningún botón presionado
    end
  // Actualización del índice del botón presionado
    if (reset) begin
      indice_boton <= 6'b10000; // Valores por defecto en caso de reset
    end else begin
      indice_boton[3:2] <= columna_actual;
      indice_boton[1:0] <= fila_actual;
      indice_boton[4] <= 1'b0;
    end

    if (~button_pressed) begin
      indice_boton <= 5'b10000;
    end

  end

endmodule

testbench/tecladoTestBench.v
`timescale 1ns / 1ps

module teclado_tb;
  // Inputs to the teclado module
  reg enable;
  reg clk;
  reg reset;
  reg [3:0] filas;

  // Outputs from the teclado module
  wire [3:0] columnas;
  wire button_pressed;
  wire [4:0] indice_boton;
  wire [2:0] columna_actual;
  wire [2:0] fila_actual;

  // Instantiate the teclado module
  teclado uut (
    .enable(enable),
    .clk(clk),
    .reset(reset),
    .filas(filas),
    .columnas(columnas),
    .indice_boton(indice_boton),
    .columna_actual(columna_actual),
    .fila_actual(fila_actual),
    .button_pressed(button_pressed)
  );

  // Clock generation
  initial begin
    clk = 0;
    forever #5 clk = ~clk; // 10 ns clock period
  end

  // Test sequence
  initial begin
    // Initialize inputs
    $dumpfile("WavesTeclado.vcd");
    $dumpvars(2);
    enable = 0;
    reset = 1;
    filas = 4'b0000;

    // Wait for global reset
    #20;
    reset = 0;

    // Enable the module
    enable = 1;

    // Test case 1: No button pressed
    filas = 4'b0000;
    #50;
    $display("Test 1: No button pressed");
    $display("indice_boton = %b, columna_actual = %b, fila_actual = %b, button_pressed = %b", 
             indice_boton, columna_actual, fila_actual, button_pressed);

    // Test case 2: Button in column 1, row 1 pressed
    filas = 4'b0001; // Row 1 active
    #50;
    $display("Test 2: Button in column 1, row 1 pressed");
    $display("indice_boton = %b, columna_actual = %b, fila_actual = %b, button_pressed = %b", 
             indice_boton, columna_actual, fila_actual, button_pressed);

    // Test case 3: Button in column 2, row 2 pressed
    filas = 4'b0010; // Row 2 active
    #50;
    $display("Test 3: Button in column 2, row 2 pressed");
    $display("indice_boton = %b, columna_actual = %b, fila_actual = %b, button_pressed = %b", 
             indice_boton, columna_actual, fila_actual, button_pressed);

    // Test case 4: Button in column 3, row 3 pressed
    filas = 4'b0100; // Row 3 active
    #50;
    $display("Test 4: Button in column 3, row 3 pressed");
    $display("indice_boton = %b, columna_actual = %b, fila_actual = %b, button_pressed = %b", 
             indice_boton, columna_actual, fila_actual, button_pressed);

    // Test case 5: Reset the system
    reset = 1;
    #20;
    reset = 0;
    #50;
    $display("Test 5: After reset");
    $display("indice_boton = %b, columna_actual = %b, fila_actual = %b, button_pressed = %b", 
             indice_boton, columna_actual, fila_actual, button_pressed);

    // End simulation
    $finish;
  end
endmodule

testbench/WavesTeclado.vcd
$date
	Fri Nov 29 19:56:03 2024
$end
$version
	Icarus Verilog
$end
$timescale
	1ps
$end
$scope module teclado_tb $end
$var wire 5 ! indice_boton [4:0] $end
$var wire 3 " fila_actual [2:0] $end
$var wire 4 # columnas [3:0] $end
$var wire 3 $ columna_actual [2:0] $end
$var wire 1 % button_pressed $end
$var reg 1 & clk $end
$var reg 1 ' enable $end
$var reg 4 ( filas [3:0] $end
$var reg 1 ) reset $end
$scope module uut $end
$var wire 1 & clk $end
$var wire 1 ' enable $end
$var wire 4 * filas [3:0] $end
$var wire 1 ) reset $end
$var wire 4 + columnas [3:0] $end
$var wire 1 % button_pressed $end
$var reg 3 , columna_actual [2:0] $end
$var reg 3 - fila_actual [2:0] $end
$var reg 5 . indice_boton [4:0] $end
$upscope $end
$upscope $end
$enddefinitions $end
$comment Show the parameter values. $end
$dumpall
$end
#0
$dumpvars
b10000 .
b111 -
b111 ,
bx +
b0 *
1)
b0 (
0'
0&
x%
b111 $
bx #
b111 "
b10000 !
$end
#5000
b1 #
b1 +
1&
#10000
0&
#15000
1&
#20000
b10000 !
b10000 .
b0 $
b0 ,
0%
0&
1'
0)
#25000
b10000 !
b10000 .
b1 $
b1 ,
b10 #
b10 +
1&
#30000
0&
#35000
b10000 !
b10000 .
b10 $
b10 ,
b100 #
b100 +
1&
#40000
0&
#45000
b10000 !
b10000 .
b11 $
b11 ,
b1000 #
b1000 +
1&
#50000
0&
#55000
b10000 !
b10000 .
b0 $
b0 ,
b1 #
b1 +
1&
#60000
0&
#65000
b10000 !
b10000 .
b1 $
b1 ,
b10 #
b10 +
1&
#70000
b0 "
b0 -
b100 !
b100 .
1%
0&
b1 (
b1 *
#75000
b1000 !
b1000 .
b10 $
b10 ,
b100 #
b100 +
1&
#80000
0&
#85000
b1100 !
b1100 .
b11 $
b11 ,
b1000 #
b1000 +
1&
#90000
0&
#95000
b0 !
b0 .
b0 $
b0 ,
b1 #
b1 +
1&
#100000
0&
#105000
b100 !
b100 .
b1 $
b1 ,
b10 #
b10 +
1&
#110000
0&
#115000
b1000 !
b1000 .
b10 $
b10 ,
b100 #
b100 +
1&
#120000
b1001 !
b1001 .
b1 "
b1 -
0&
b10 (
b10 *
#125000
b1101 !
b1101 .
b11 $
b11 ,
b1000 #
b1000 +
1&
#130000
0&
#135000
b1 !
b1 .
b0 $
b0 ,
b1 #
b1 +
1&
#140000
0&
#145000
b101 !
b101 .
b1 $
b1 ,
b10 #
b10 +
1&
#150000
0&
#155000
b1001 !
b1001 .
b10 $
b10 ,
b100 #
b100 +
1&
#160000
0&
#165000
b1101 !
b1101 .
b11 $
b11 ,
b1000 #
b1000 +
1&
#170000
b1110 !
b1110 .
b10 "
b10 -
0&
b100 (
b100 *
#175000
b10 !
b10 .
b0 $
b0 ,
b1 #
b1 +
1&
#180000
0&
#185000
b110 !
b110 .
b1 $
b1 ,
b10 #
b10 +
1&
#190000
0&
#195000
b1010 !
b1010 .
b10 $
b10 ,
b100 #
b100 +
1&
#200000
0&
#205000
b1110 !
b1110 .
b11 $
b11 ,
b1000 #
b1000 +
1&
#210000
0&
#215000
b10 !
b10 .
b0 $
b0 ,
b1 #
b1 +
1&
#220000
b10000 !
b10000 .
0&
1)
#225000
1&
#230000
0&
#235000
1&
#240000
b10 !
b10 .
0&
0)
#245000
b110 !
b110 .
b1 $
b1 ,
b10 #
b10 +
1&
#250000
0&
#255000
b1010 !
b1010 .
b10 $
b10 ,
b100 #
b100 +
1&
#260000
0&
#265000
b1110 !
b1110 .
b11 $
b11 ,
b1000 #
b1000 +
1&
#270000
0&
#275000
b10 !
b10 .
b0 $
b0 ,
b1 #
b1 +
1&
#280000
0&
#285000
b110 !
b110 .
b1 $
b1 ,
b10 #
b10 +
1&
